resotonotebook/__init__.py
resotonotebook/client.py
resotonotebook/pyodide_client.py
resotonotebook-0.2.2.dist-info/LICENSE
resotonotebook-0.2.2.dist-info/WHEEL
resotonotebook-0.2.2.dist-info/METADATA
resotonotebook-0.2.2.dist-info/RECORD
